git_review/__init__.py
git_review/cmd.py
git_review/hooks.py
git_review/tests/__init__.py
git_review/tests/check_test_id_hashes.py
git_review/tests/prepare.py
git_review/tests/test_git_review.py
git_review/tests/test_unit.py
git_review/tests/utils.py
git_review-2.5.0.data/data/share/man/man1/git-review.1
git_review-2.5.0.dist-info/licenses/AUTHORS
git_review-2.5.0.dist-info/licenses/LICENSE
git_review-2.5.0.dist-info/METADATA
git_review-2.5.0.dist-info/WHEEL
git_review-2.5.0.dist-info/entry_points.txt
git_review-2.5.0.dist-info/pbr.json
git_review-2.5.0.dist-info/top_level.txt
git_review-2.5.0.dist-info/RECORD
